Metadata-Version: 2.1
Name: barbudor-circuitpython-ina3221
Version: 1.2.0
Summary: CircuitPython library for INA3221 triple channel current sensor.
Home-page: https://github.com/barbudor/CircuitPython_INA3221
Author: Barbudor
Author-email: barbudor@barbudor.net
License: MIT
Download-URL: https://github.com/barbudor/CircuitPython_INA3221/archive/1.2.0.tar.gz
Keywords: current sensor I2C breakout hardware micropython circuitpython
Platform: UNKNOWN
Classifier: Development Status :: 3 - Alpha
Classifier: Intended Audience :: Developers
Classifier: Topic :: Software Development :: Libraries
Classifier: Topic :: System :: Hardware
Classifier: License :: OSI Approved :: MIT License
Classifier: Programming Language :: Python :: 3
Classifier: Programming Language :: Python :: 3.4
Classifier: Programming Language :: Python :: 3.5
